ezflake/__init__.py
ezflake/plugin.py
ezflake/testing.py
ezflake/utils.py
ezflake/violation.py
ezflake-2.1.0.dist-info/LICENSE
ezflake-2.1.0.dist-info/METADATA
ezflake-2.1.0.dist-info/WHEEL
ezflake-2.1.0.dist-info/top_level.txt
ezflake-2.1.0.dist-info/RECORD
